aplicacion_ejemplo/__init__.py
aplicacion_ejemplo/ejemplo.py
aplicacion_ejemplo_kc-0.0.1.dist-info/METADATA
aplicacion_ejemplo_kc-0.0.1.dist-info/WHEEL
aplicacion_ejemplo_kc-0.0.1.dist-info/top_level.txt
aplicacion_ejemplo_kc-0.0.1.dist-info/RECORD
