Metadata-Version: 2.1
Name: aplicacion-ejemplo-kc
Version: 0.0.1
Summary: A small example package
Author: Marta Arcones
Author-email: marta.arcones@gmail.com
License: UNKNOWN
Platform: UNKNOWN
Requires-Python: >=3.9
Requires-Dist: coloredlogs
